numpsy/__init__.py
numpsy/configuration.py
numpsy/constants.py
numpsy/core.py
numpsy/functions.py
numpsy/helpers.py
numpsy/printers.py
numpsy/units.py
numpsy-0.0.12.dist-info/LICENSE
numpsy-0.0.12.dist-info/METADATA
numpsy-0.0.12.dist-info/WHEEL
numpsy-0.0.12.dist-info/top_level.txt
numpsy-0.0.12.dist-info/RECORD
