Metadata-Version: 2.1
Name: numpsy
Version: 0.0.12
Summary: NumpSy - Integrated NumPy, SymPy, SciPy and Pandas with unit management for scientific programming with IPython.
Home-page: https://github.com/daquintero/numpsy
Author: Dario Quintero
Author-email: darioaquintero@gmail.com
Classifier: Programming Language :: Python :: 3
Classifier: License :: OSI Approved :: MIT License
Classifier: Operating System :: OS Independent
Requires-Python: >=3.6
License-File: LICENSE
